templated_docs/__init__.py
templated_docs/http.py
templated_docs/management/__init__.py
templated_docs/management/base.py
templated_docs/templatetags/__init__.py
templated_docs/templatetags/templated_docs_tags.py
templateddocs-0.3.3.dist-info/DESCRIPTION.rst
templateddocs-0.3.3.dist-info/METADATA
templateddocs-0.3.3.dist-info/RECORD
templateddocs-0.3.3.dist-info/WHEEL
templateddocs-0.3.3.dist-info/metadata.json
templateddocs-0.3.3.dist-info/top_level.txt
tests/__init__.py
tests/manage.py
tests/test_app/__init__.py
tests/test_app/admin.py
tests/test_app/apps.py
tests/test_app/models.py
tests/test_app/tests.py
tests/test_app/views.py
tests/test_app/migrations/__init__.py
tests/test_app/templates/correct_template.odt
tests/test_project/__init__.py
tests/test_project/settings.py
tests/test_project/urls.py
tests/test_project/wsgi.py
