Metadata-Version: 2.0
Name: templateddocs
Version: 0.3.3
Summary: Generate PDF, MS Word and Excel documents from templates in Django.
Home-page: https://github.com/kiawin/templated-docs
Author: Sian Lerk Lau
Author-email: kiawin@gmail.com
License: MIT license
Keywords: templateddocs
Platform: UNKNOWN
Classifier: Development Status :: 2 - Pre-Alpha
Classifier: Intended Audience :: Developers
Classifier: License :: OSI Approved :: MIT License
Classifier: Natural Language :: English
Classifier: Programming Language :: Python :: 2
Classifier: Programming Language :: Python :: 2.7
Classifier: Programming Language :: Python :: 3
Classifier: Programming Language :: Python :: 3.3
Classifier: Programming Language :: Python :: 3.4
Classifier: Programming Language :: Python :: 3.5
Classifier: Programming Language :: Python :: 3.6
Classifier: Programming Language :: Python :: 3.7
Requires-Dist: django (<1.12,>=1.8)
Requires-Dist: pylokit (==0.8.1)
